{"stats":{"minecraft:crafted":{"minecraft:oak_planks":4,"minecraft:crafting_table":1,"createlectrified:aluminium_ingot":9,"createlectrified:electrum_block":1,"createlectrified:electrum":9,"createlectrified:aluminium_block":9},"minecraft:dropped":{"create:turntable":1,"createlectrified:aluminium_sheet":1,"minecraft:paper":1,"createlectrified:bauxite_ore":1},"minecraft:used":{"minecraft:netherite_block":1,"create:zinc_block":1,"create:brass_block":1,"create:mechanical_press":1,"minecraft:carved_pumpkin":5,"minecraft:iron_block":2,"minecraft:grass_block":2,"minecraft:netherite_axe":1,"minecraft:copper_block":1,"minecraft:sheep_spawn_egg":1,"minecraft:raw_gold_block":1,"create:creative_motor":2,"createlectrified:electrum_block":23,"minecraft:waxed_copper_block":1,"minecraft:orange_carpet":11,"create:turntable":2,"minecraft:diamond_block":2,"minecraft:raw_copper_block":1,"minecraft:cobblestone":4,"minecraft:beef":3,"create:mechanical_mixer":1,"minecraft:emerald_block":1,"minecraft:sea_pickle":4,"minecraft:crafting_table":1,"createlectrified:raw_aluminium_block":2,"minecraft:raw_iron_block":1,"create:cogwheel":3,"createlectrified:aluminium_block":2,"minecraft:netherite_pickaxe":23,"minecraft:gold_block":1,"create:depot":1,"create:vertical_gearbox":2,"createlectrified:aluminium_casing":23,"minecraft:pumpkin":25},"minecraft:mined":{"createlectrified:aluminium_block":1,"createlectrified:aluminium_casing":11,"minecraft:waxed_copper_block":1,"minecraft:diamond_block":1,"create:zinc_block":1,"minecraft:gold_block":1,"minecraft:grass":1,"minecraft:oak_log":1,"create:brass_block":1,"createlectrified:electrum_block":2,"minecraft:iron_block":1,"minecraft:emerald_block":1},"minecraft:picked_up":{"minecraft:emerald_block":1,"minecraft:leather":2,"createlectrified:electrum_block":2,"minecraft:gold_block":1,"createlectrified:aluminium_casing":11,"create:brass_block":1,"minecraft:oak_log":1,"minecraft:waxed_copper_block":1,"createlectrified:bauxite_ore":1,"create:turntable":1,"minecraft:diamond_block":1,"createlectrified:aluminium_sheet":1,"minecraft:paper":1,"minecraft:iron_block":1,"minecraft:beef":3,"create:zinc_block":1,"createlectrified:aluminium_block":1},"minecraft:killed":{"minecraft:cow":1},"minecraft:custom":{"minecraft:time_since_rest":17044,"minecraft:sprint_one_cm":21086,"minecraft:walk_one_cm":20386,"minecraft:mob_kills":1,"minecraft:drop":4,"minecraft:damage_dealt":110,"minecraft:swim_one_cm":813,"minecraft:interact_with_crafting_table":1,"minecraft:fly_one_cm":259735,"minecraft:open_chest":2,"minecraft:crouch_one_cm":1359,"minecraft:play_time":43478,"minecraft:deaths":1,"minecraft:sneak_time":1019,"minecraft:walk_under_water_one_cm":1140,"minecraft:jump":245,"minecraft:leave_game":8,"minecraft:time_since_death":17018,"minecraft:walk_on_water_one_cm":701,"minecraft:total_world_time":46640,"minecraft:fall_one_cm":1254}},"DataVersion":3120}